<?xml version="1.0" encoding="UTF-8"?>
<!-- 
/**
 * Copyright (c) 2005-2008 Intalio inc.
 *
 * All rights reserved. This program and the accompanying materials
 * are made available under the terms of the Eclipse Public License v1.0
 * which accompanies this distribution, and is available at
 * http://www.eclipse.org/legal/epl-v10.html
 *
 * Contributors:
 * Intalio inc. - initial API and implementation
 */
 -->
<serviceGroup>
    <service name="TaskManagementServices" class="org.intalio.tempo.workflow.SpringInit">
        <description>Intalio|BPMS Task Management Services</description>

        <parameter name="SpringContextFile">file:${org.intalio.tempo.configDirectory}/tempo-tms.xml</parameter>
        <parameter name="ServiceObjectSupplier">org.intalio.tempo.workflow.ServiceObjectSupplier</parameter>
        <parameter name="SpringBeanName">tms.serviceImplementation</parameter>
        <!-- Needed so that it can initialize the bean for audit also. Created for WF-1574-->
        <parameter name="LoadAllBeansOnStartup">true</parameter>
        <!-- 
          Needed so that the deployment service starts straight on server startup. 
          Since the code for pipa deployment is located in TMS.
        -->
        <parameter name="LoadOnStartup">true</parameter>

        <operation name="getTaskList">
            <messageReceiver class="org.apache.axis2.receivers.RawXMLINOutMessageReceiver"/>
            <actionMapping>http://www.intalio.com/BPMS/Workflow/TaskManagementServices-20051109/getTaskList</actionMapping>
        </operation>
        
        <operation name="listTasksFromInstance">
            <messageReceiver class="org.apache.axis2.receivers.RawXMLINOutMessageReceiver"/>
            <actionMapping>http://www.intalio.com/BPMS/Workflow/TaskManagementServices-20051109/listTasksFromInstance</actionMapping>
        </operation>

        <operation name="getTask">
            <messageReceiver class="org.apache.axis2.receivers.RawXMLINOutMessageReceiver"/>
            <actionMapping>http://www.intalio.com/BPMS/Workflow/TaskManagementServices-20051109/getTask</actionMapping>
        </operation>
        
		<operation name="getTaskOwnerAndState">
            <messageReceiver class="org.apache.axis2.receivers.RawXMLINOutMessageReceiver"/>
            <actionMapping>http://www.intalio.com/BPMS/Workflow/TaskManagementServices-20051109/getTaskOwnerAndState</actionMapping>
        </operation>
		
        <operation name="skip">
            <messageReceiver class="org.apache.axis2.receivers.RawXMLINOutMessageReceiver"/>
            <actionMapping>http://www.intalio.com/BPMS/Workflow/TaskManagementServices-20051109/skip</actionMapping>
        </operation>

        <operation name="setOutput">
            <messageReceiver class="org.apache.axis2.receivers.RawXMLINOutMessageReceiver"/>
            <actionMapping>http://www.intalio.com/BPMS/Workflow/TaskManagementServices-20051109/setOutput</actionMapping>
        </operation>

        <operation name="setOutputAndComplete">
            <messageReceiver class="org.apache.axis2.receivers.RawXMLINOutMessageReceiver"/>
            <actionMapping>http://www.intalio.com/BPMS/Workflow/TaskManagementServices-20051109/setOutputAndComplete</actionMapping>
        </operation>

        <operation name="complete">
            <messageReceiver class="org.apache.axis2.receivers.RawXMLINOutMessageReceiver"/>
            <actionMapping>http://www.intalio.com/BPMS/Workflow/TaskManagementServices-20051109/complete</actionMapping>
        </operation>

        <operation name="fail">
            <messageReceiver class="org.apache.axis2.receivers.RawXMLINOutMessageReceiver"/>
            <actionMapping>http://www.intalio.com/BPMS/Workflow/TaskManagementServices-20051109/fail</actionMapping>
        </operation>

        <operation name="delete">
            <messageReceiver class="org.apache.axis2.receivers.RawXMLINOutMessageReceiver"/>
            <actionMapping>http://www.intalio.com/BPMS/Workflow/TaskManagementServices-20051109/delete</actionMapping>
        </operation>
       
        <operation name="manageFromInstance">
            <messageReceiver class="org.apache.axis2.receivers.RawXMLINOutMessageReceiver"/>
            <actionMapping>http://www.intalio.com/BPMS/Workflow/TaskManagementServices-20051109/manageFromInstance</actionMapping>
        </operation>
        
        <operation name="create">
            <messageReceiver class="org.apache.axis2.receivers.RawXMLINOutMessageReceiver"/>
            <actionMapping>http://www.intalio.com/BPMS/Workflow/TaskManagementServices-20051109/create</actionMapping>
        </operation>

        <operation name="update">
            <messageReceiver class="org.apache.axis2.receivers.RawXMLINOutMessageReceiver"/>
            <actionMapping>http://www.intalio.com/BPMS/Workflow/TaskManagementServices-20051109/update</actionMapping>
        </operation>

        <operation name="initProcess">
            <messageReceiver class="org.apache.axis2.receivers.RawXMLINOutMessageReceiver"/>
            <actionMapping>http://www.intalio.com/BPMS/Workflow/TaskManagementServices-20051109/initProcess</actionMapping>
        </operation>

        <operation name="getAttachments">
            <messageReceiver class="org.apache.axis2.receivers.RawXMLINOutMessageReceiver"/>
            <actionMapping>http://www.intalio.com/BPMS/Workflow/TaskManagementServices-20051109/getAttachments</actionMapping>
        </operation>

        <operation name="addAttachment">
            <messageReceiver class="org.apache.axis2.receivers.RawXMLINOutMessageReceiver"/>
            <actionMapping>http://www.intalio.com/BPMS/Workflow/TaskManagementServices-20051109/addAttachment</actionMapping>
        </operation>

        <operation name="removeAttachment">
            <messageReceiver class="org.apache.axis2.receivers.RawXMLINOutMessageReceiver"/>
            <actionMapping>http://www.intalio.com/BPMS/Workflow/TaskManagementServices-20051109/removeAttachment</actionMapping>
        </operation>

        <operation name="reassign">
            <messageReceiver class="org.apache.axis2.receivers.RawXMLINOutMessageReceiver"/>
            <actionMapping>http://www.intalio.com/BPMS/Workflow/TaskManagementServices-20051109/reassign</actionMapping>
        </operation>
        
        <operation name="storePipa">
            <messageReceiver class="org.apache.axis2.receivers.RawXMLINOutMessageReceiver"/>
            <actionMapping>http://www.intalio.com/BPMS/Workflow/TaskManagementServices-20051109/storePipa</actionMapping>
        </operation>
        
        <operation name="deletePipa">
            <messageReceiver class="org.apache.axis2.receivers.RawXMLINOutMessageReceiver"/>
            <actionMapping>http://www.intalio.com/BPMS/Workflow/TaskManagementServices-20051109/deletePipa</actionMapping>
        </operation>
        
        <operation name="deleteAll">
            <messageReceiver class="org.apache.axis2.receivers.RawXMLINOutMessageReceiver"/>
            <actionMapping>http://www.intalio.com/BPMS/Workflow/TaskManagementServices-20051109/deleteAll</actionMapping>
        </operation>
        
        <operation name="getPipa">
            <messageReceiver class="org.apache.axis2.receivers.RawXMLINOutMessageReceiver"/>
            <actionMapping>http://www.intalio.com/BPMS/Workflow/TaskManagementServices-20051109/getPipa</actionMapping>
        </operation>
        
        <operation name="getAvailableTasks">
            <messageReceiver class="org.apache.axis2.receivers.RawXMLINOutMessageReceiver"/>
            <actionMapping>http://www.intalio.com/BPMS/Workflow/TaskManagementServices-20051109/getAvailableTasks</actionMapping>
        </operation>
        
        <operation name="countAvailableTasks">
            <messageReceiver class="org.apache.axis2.receivers.RawXMLINOutMessageReceiver"/>
            <actionMapping>http://www.intalio.com/BPMS/Workflow/TaskManagementServices-20051109/countAvailableTasks</actionMapping>
        </operation>
        <operation name="getCustomColumns">
            <messageReceiver class="org.apache.axis2.receivers.RawXMLINOutMessageReceiver"/>
            <actionMapping>http://www.intalio.com/BPMS/Workflow/TaskManagementServices-20051109/getCustomColumns</actionMapping>
        </operation>        
        <operation name="clearCache">
            <messageReceiver class="org.apache.axis2.receivers.RawXMLINOnlyMessageReceiver"/>
            <actionMapping>http://www.intalio.com/BPMS/Workflow/TaskManagementServices-20051109/clearCache</actionMapping>
        </operation>
        <operation name="insertVacation">
            <messageReceiver class="org.apache.axis2.receivers.RawXMLINOutMessageReceiver"/>
            <actionMapping>http://www.intalio.com/BPMS/Workflow/TaskManagementServices-20051109/insertVacation</actionMapping>
        </operation>
        <operation name="getUserVacation">
            <messageReceiver class="org.apache.axis2.receivers.RawXMLINOutMessageReceiver"/>
            <actionMapping>http://www.intalio.com/BPMS/Workflow/TaskManagementServices-20051109/getUserVacation</actionMapping>
        </operation>
        <operation name="getVacationList">
            <messageReceiver class="org.apache.axis2.receivers.RawXMLINOutMessageReceiver"/>
            <actionMapping>http://www.intalio.com/BPMS/Workflow/TaskManagementServices-20051109/getVacationList</actionMapping>
        </operation>
        <operation name="deleteVacation">
            <messageReceiver class="org.apache.axis2.receivers.RawXMLINOutMessageReceiver"/>
            <actionMapping>http://www.intalio.com/BPMS/Workflow/TaskManagementServices-20051109/deleteVacation</actionMapping>
        </operation>
        <operation name="updatePipa">
            <messageReceiver class="org.apache.axis2.receivers.RawXMLINOutMessageReceiver"/>
            <actionMapping>http://www.intalio.com/BPMS/Workflow/TaskManagementServices-20051109/updatePipa</actionMapping>
        </operation>        
    </service>
</serviceGroup>
